LICENSE
MANIFEST.in
README.rst
setup.py
ftpext/__init__.py
ftpext/ftpext.py
ftpext.egg-info/PKG-INFO
ftpext.egg-info/SOURCES.txt
ftpext.egg-info/dependency_links.txt
ftpext.egg-info/not-zip-safe
ftpext.egg-info/top_level.txt