Metadata-Version: 1.1
Name: ftpext
Version: 0.1.0
Summary: extensions to the 'ftplib' module
Home-page: https://github.com/kalind/ftpext
Author: Kalle Lindqvist
Author-email: kalle.lindqvist@mykolab.com
License: BSD
Keywords: ftpext,FTP,client,library
Platform: UNKNOWN
Classifier: Intended Audience :: Developers
Classifier: Intended Audience :: System Administrators
Classifier: License :: OSI Approved :: BSD License
Classifier: Topic :: Internet :: File Transfer Protocol (FTP)
Classifier: Programming Language :: Python :: 3
